PSSimPy/__init__.py
PSSimPy/account.py
PSSimPy/bank.py
PSSimPy/system.py
PSSimPy/transaction.py
PSSimPy/constraint_handler/__init__.py
PSSimPy/constraint_handler/abstract_constraint_handler.py
PSSimPy/constraint_handler/max_size_constraint_handler.py
PSSimPy/constraint_handler/min_balance_constraint_handler.py
PSSimPy/constraint_handler/pass_through_handler.py
PSSimPy/credit_facilities/__init__.py
PSSimPy/credit_facilities/abstract_credit_facility.py
PSSimPy/credit_facilities/simple_collateralized.py
PSSimPy/credit_facilities/simple_priced.py
PSSimPy/queues/__init__.py
PSSimPy/queues/abstract_queue.py
PSSimPy/queues/direct_queue.py
PSSimPy/queues/fifo_queue.py
PSSimPy/queues/priority_queue.py
PSSimPy/simulator/__init__.py
PSSimPy/simulator/abm_sim.py
PSSimPy/simulator/basic_sim.py
PSSimPy/transaction_fee/__init__.py
PSSimPy/transaction_fee/abstract_transaction_fee.py
PSSimPy/transaction_fee/fixed_transaction_fee.py
PSSimPy/utils/__init__.py
PSSimPy/utils/account_utils.py
PSSimPy/utils/constants.py
PSSimPy/utils/data_utils.py
PSSimPy/utils/file_utils.py
PSSimPy/utils/logger.py
PSSimPy/utils/time_utils.py
PSSimPy/utils/transaction_utils.py
PSSimPy-0.1.5.dist-info/LICENSE
PSSimPy-0.1.5.dist-info/METADATA
PSSimPy-0.1.5.dist-info/WHEEL
PSSimPy-0.1.5.dist-info/top_level.txt
PSSimPy-0.1.5.dist-info/RECORD
