Metadata-Version: 2.1
Name: PSSimPy
Version: 0.1.5
Summary: A simulator for Large Value Payment Systems
Home-page: UNKNOWN
Author: Kenneth See, Hanzholah Shobri
Author-email: see.k@u.nus.edu, hanzhshobri@gmail.com
License: UNKNOWN
Platform: UNKNOWN
Requires-Dist: numpy>=1.22.4
Requires-Dist: pandas>=2.0.0
Requires-Dist: sortedcontainers==2.4.0
Requires-Dist: simpy==4.1.1
